setup.py
qtxpack/__init__.py
qtxpack.egg-info/PKG-INFO
qtxpack.egg-info/SOURCES.txt
qtxpack.egg-info/dependency_links.txt
qtxpack.egg-info/not-zip-safe
qtxpack.egg-info/requires.txt
qtxpack.egg-info/top_level.txt