Metadata-Version: 1.0
Name: qtxpack
Version: 1.0
Summary: package to generate db connections
Home-page: http://github.com/storborg/funniest
Author: Flying Circus
Author-email: flyingcircus@example.com
License: MIT
Platform: UNKNOWN
